<?xml version="1.0" encoding="utf-8"?>
<inspection>
  <date></date>
  <time></time>
  <staff></staff>
  <orderNo></orderNo>
  <drawing></drawing>
  <product_name></product_name>
  <deadline></deadline>
  <dimension1></dimension1>
  <dimension2></dimension2>
  <dimension3></dimension3>
  <dimension4></dimension4>
  <dimension5></dimension5>
  <dimension6></dimension6>
  <dimension7></dimension7>
  <dimension8></dimension8>
  <dimension9></dimension9>
  <dimension10></dimension10>
  <dimension11></dimension11>
  <dimension12></dimension12>
  <dimension13></dimension13>
</inspection>